cubevis/LICENSE.rst
cubevis/__icons__/20px/fast-backward.svg
cubevis/__icons__/20px/fast-forward.svg
cubevis/__icons__/20px/step-backward.svg
cubevis/__icons__/20px/step-forward.svg
cubevis/__icons__/add-chan.png
cubevis/__icons__/add-chan.svg
cubevis/__icons__/add-cube.png
cubevis/__icons__/add-cube.svg
cubevis/__icons__/drag.png
cubevis/__icons__/drag.svg
cubevis/__icons__/mask-selected.png
cubevis/__icons__/mask.png
cubevis/__icons__/mask.svg
cubevis/__icons__/new-layer-sm-selected.png
cubevis/__icons__/new-layer-sm-selected.svg
cubevis/__icons__/new-layer-sm.png
cubevis/__icons__/new-layer-sm.svg
cubevis/__icons__/reset.png
cubevis/__icons__/reset.svg
cubevis/__icons__/sub-chan.png
cubevis/__icons__/sub-chan.svg
cubevis/__icons__/sub-cube.png
cubevis/__icons__/sub-cube.svg
cubevis/__icons__/trash.png
cubevis/__icons__/trash.svg
cubevis/__icons__/trash_full.png
cubevis/__icons__/trash_full.svg
cubevis/__icons__/trash_full_raw.png
cubevis/__icons__/zoom-to-fit.png
cubevis/__icons__/zoom-to-fit.svg
cubevis/__init__.py
cubevis/__js__/bokeh-3.6/cubevisjs.min.js
cubevis/__js__/bokeh-3.7/cubevisjs.min.js
cubevis/__js__/bokeh-3.8/cubevisjs.min.js
cubevis/__js__/casalib.min.js
cubevis/bokeh/__init__.py
cubevis/bokeh/annotations/__init__.py
cubevis/bokeh/annotations/_ev_poly_annotation.py
cubevis/bokeh/components/__init__.py
cubevis/bokeh/format/__init__.py
cubevis/bokeh/format/_time_ticks.py
cubevis/bokeh/format/_wcs_ticks.py
cubevis/bokeh/models/__init__.py
cubevis/bokeh/models/_bokeh_app_context.py
cubevis/bokeh/models/_edit_span.py
cubevis/bokeh/models/_ev_text_input.py
cubevis/bokeh/models/_shared_dict.py
cubevis/bokeh/models/_showable.py
cubevis/bokeh/models/_tip.py
cubevis/bokeh/models/_tip_button.py
cubevis/bokeh/sources/__init__.py
cubevis/bokeh/sources/_data_pipe.py
cubevis/bokeh/sources/_image_data_source.py
cubevis/bokeh/sources/_image_pipe.py
cubevis/bokeh/sources/_spectra_data_source.py
cubevis/bokeh/sources/_updatable_data_source.py
cubevis-1.0.65.dist-info/WHEEL
cubevis-1.0.65.dist-info/METADATA
cubevis-1.0.65.dist-info/licenses/LICENSE
cubevis-1.0.65.dist-info/RECORD
