Metadata-Version: 2.1
Name: cubevis
Version: 1.0.65
Summary: visualization toolkit and apps for casa
License: LGPL
Author-email: Darrell Schiebel <darrell@schiebel.us>,Pam Harris <pharris@nrao.edu>
Requires-Python: >=3.11
Requires-Dist: astropy>=5.1
Requires-Dist: bokeh<3.9,>=3.6
Requires-Dist: certifi
Requires-Dist: matplotlib
Requires-Dist: regions>=0.8
Requires-Dist: websockets>=10.3
Project-URL: Bug Tracker, https://github.com/casangi/cubevis/issues
Project-URL: Homepage, https://github.com/casangi/cubevis?tab=readme-ov-file#cubevis---visualization-tools-for-casa-images
Project-URL: Source, https://github.com/casangi/cubevis
